[
    {
        "description": "TONART",
        "isreplacecandidate": false,
        "isreplaced": false,
        "value": -1,
        "isprobability": false,
        "generatemin": -1,
        "generatemax": -1,
        "isreplicated": false,
        "clonenr": 1,
        "isreplicatecandidate": false,
        "isoriginal": true,
        "children": [
            {
                "description": "F",
                "isreplacecandidate": false,
                "isreplaced": false,
                "value": 10,
                "isprobability": true,
                "generatemin": -1,
                "generatemax": -1,
                "isreplicated": false,
                "clonenr": 1,
                "isreplicatecandidate": false,
                "isoriginal": false
            },
            {
                "description": "C",
                "isreplacecandidate": false,
                "isreplaced": false,
                "value": 10,
                "isprobability": true,
                "generatemin": -1,
                "generatemax": -1,
                "isreplicated": false,
                "clonenr": 1,
                "isreplicatecandidate": false,
                "isoriginal": false
            },
            {
                "description": "G",
                "isreplacecandidate": false,
                "isreplaced": false,
                "value": 10,
                "isprobability": true,
                "generatemin": -1,
                "generatemax": -1,
                "isreplicated": false,
                "clonenr": 1,
                "isreplicatecandidate": false,
                "isoriginal": false
            },
            {
                "description": "a",
                "isreplacecandidate": false,
                "isreplaced": false,
                "value": 10,
                "isprobability": true,
                "generatemin": -1,
                "generatemax": -1,
                "isreplicated": false,
                "clonenr": 1,
                "isreplicatecandidate": false,
                "isoriginal": false
            },
            {
                "description": "d",
                "isreplacecandidate": false,
                "isreplaced": false,
                "value": 10,
                "isprobability": true,
                "generatemin": -1,
                "generatemax": -1,
                "isreplicated": false,
                "clonenr": 1,
                "isreplicatecandidate": false,
                "isoriginal": false
            },
            {
                "description": "e",
                "isreplacecandidate": false,
                "isreplaced": false,
                "value": 10,
                "isprobability": true,
                "generatemin": -1,
                "generatemax": -1,
                "isreplicated": false,
                "clonenr": 1,
                "isreplicatecandidate": false,
                "isoriginal": false
            }
        ]
    },
    {
        "description": "MC_major",
        "isreplacecandidate": false,
        "isreplaced": false,
        "value": -1,
        "isprobability": false,
        "generatemin": -1,
        "generatemax": -1,
        "isreplicated": false,
        "clonenr": 1,
        "isreplicatecandidate": false,
        "isoriginal": true,
        "children": [
            {
                "description": "type",
                "isreplacecandidate": false,
                "isreplaced": false,
                "value": -1,
                "isprobability": false,
                "generatemin": -1,
                "generatemax": -1,
                "isreplicated": false,
                "clonenr": 1,
                "isreplicatecandidate": false,
                "isoriginal": false,
                "children": [
                    {
                        "description": "V",
                        "isreplacecandidate": false,
                        "isreplaced": false,
                        "value": 10,
                        "isprobability": true,
                        "generatemin": -1,
                        "generatemax": -1,
                        "isreplicated": false,
                        "clonenr": 1,
                        "isreplicatecandidate": false,
                        "isoriginal": false
                    },
                    {
                        "description": "V7",
                        "isreplacecandidate": false,
                        "isreplaced": false,
                        "value": 10,
                        "isprobability": true,
                        "generatemin": -1,
                        "generatemax": -1,
                        "isreplicated": false,
                        "clonenr": 1,
                        "isreplicatecandidate": false,
                        "isoriginal": false
                    }
                ]
            },
            {
                "description": "type",
                "isreplacecandidate": false,
                "isreplaced": false,
                "value": -1,
                "isprobability": false,
                "generatemin": -1,
                "generatemax": -1,
                "isreplicated": false,
                "clonenr": 1,
                "isreplicatecandidate": false,
                "isoriginal": false,
                "children": [
                    {
                        "description": "V",
                        "isreplacecandidate": false,
                        "isreplaced": false,
                        "value": -1,
                        "isprobability": false,
                        "generatemin": -1,
                        "generatemax": -1,
                        "isreplicated": false,
                        "clonenr": 1,
                        "isreplicatecandidate": false,
                        "isoriginal": false
                    },
                    {
                        "description": "V7",
                        "isreplacecandidate": false,
                        "isreplaced": false,
                        "value": -1,
                        "isprobability": false,
                        "generatemin": -1,
                        "generatemax": -1,
                        "isreplicated": false,
                        "clonenr": 1,
                        "isreplicatecandidate": false,
                        "isoriginal": false
                    }
                ]
            },
            {
                "description": "I",
                "isreplacecandidate": false,
                "isreplaced": false,
                "value": -1,
                "isprobability": false,
                "generatemin": -1,
                "generatemax": -1,
                "isreplicated": false,
                "clonenr": 1,
                "isreplicatecandidate": false,
                "isoriginal": false
            }
        ]
    },
    {
        "description": "MC_minor",
        "isreplacecandidate": false,
        "isreplaced": false,
        "value": -1,
        "isprobability": false,
        "generatemin": -1,
        "generatemax": -1,
        "isreplicated": false,
        "clonenr": 1,
        "isreplicatecandidate": false,
        "isoriginal": true,
        "children": [
            {
                "description": "type",
                "isreplacecandidate": false,
                "isreplaced": false,
                "value": -1,
                "isprobability": false,
                "generatemin": -1,
                "generatemax": -1,
                "isreplicated": false,
                "clonenr": 1,
                "isreplicatecandidate": false,
                "isoriginal": false,
                "children": [
                    {
                        "description": "V",
                        "isreplacecandidate": false,
                        "isreplaced": false,
                        "value": 10,
                        "isprobability": true,
                        "generatemin": -1,
                        "generatemax": -1,
                        "isreplicated": false,
                        "clonenr": 1,
                        "isreplicatecandidate": false,
                        "isoriginal": false
                    },
                    {
                        "description": "V7",
                        "isreplacecandidate": false,
                        "isreplaced": false,
                        "value": 10,
                        "isprobability": true,
                        "generatemin": -1,
                        "generatemax": -1,
                        "isreplicated": false,
                        "clonenr": 1,
                        "isreplicatecandidate": false,
                        "isoriginal": false
                    }
                ]
            },
            {
                "description": "type",
                "isreplacecandidate": false,
                "isreplaced": false,
                "value": -1,
                "isprobability": false,
                "generatemin": -1,
                "generatemax": -1,
                "isreplicated": false,
                "clonenr": 1,
                "isreplicatecandidate": false,
                "isoriginal": false,
                "children": [
                    {
                        "description": "V",
                        "isreplacecandidate": false,
                        "isreplaced": false,
                        "value": -1,
                        "isprobability": false,
                        "generatemin": -1,
                        "generatemax": -1,
                        "isreplicated": false,
                        "clonenr": 1,
                        "isreplicatecandidate": false,
                        "isoriginal": false
                    },
                    {
                        "description": "V7",
                        "isreplacecandidate": false,
                        "isreplaced": false,
                        "value": -1,
                        "isprobability": false,
                        "generatemin": -1,
                        "generatemax": -1,
                        "isreplicated": false,
                        "clonenr": 1,
                        "isreplicatecandidate": false,
                        "isoriginal": false
                    }
                ]
            },
            {
                "description": "i",
                "isreplacecandidate": false,
                "isreplaced": false,
                "value": -1,
                "isprobability": false,
                "generatemin": -1,
                "generatemax": -1,
                "isreplicated": false,
                "clonenr": 1,
                "isreplicatecandidate": false,
                "isoriginal": false
            }
        ]
    },
    {
        "description": "mini_cadence",
        "isreplacecandidate": false,
        "isreplaced": false,
        "value": -1,
        "isprobability": false,
        "generatemin": -1,
        "generatemax": -1,
        "isreplicated": false,
        "clonenr": 1,
        "isreplicatecandidate": false,
        "isoriginal": true,
        "children": [
            {
                "description": "x",
                "isreplacecandidate": false,
                "isreplaced": false,
                "value": -1,
                "isprobability": false,
                "generatemin": 1,
                "generatemax": 1,
                "isreplicated": false,
                "clonenr": 1,
                "isreplicatecandidate": true,
                "isoriginal": false
            },
            {
                "description": "MC_major",
                "isreplacecandidate": true,
                "isreplaced": false,
                "value": -1,
                "isprobability": false,
                "generatemin": -1,
                "generatemax": -1,
                "isreplicated": false,
                "clonenr": 1,
                "isreplicatecandidate": false,
                "isoriginal": false
            },
            {
                "description": "x",
                "isreplacecandidate": false,
                "isreplaced": false,
                "value": -1,
                "isprobability": false,
                "generatemin": 1,
                "generatemax": 1,
                "isreplicated": false,
                "clonenr": 1,
                "isreplicatecandidate": true,
                "isoriginal": false
            }
        ]
    },
    {
        "description": "SECTION",
        "isreplacecandidate": false,
        "isreplaced": false,
        "value": -1,
        "isprobability": false,
        "generatemin": -1,
        "generatemax": -1,
        "isreplicated": false,
        "clonenr": 1,
        "isreplicatecandidate": false,
        "isoriginal": true,
        "children": [
            {
                "description": "TONART_A",
                "isreplacecandidate": false,
                "isreplaced": false,
                "value": -1,
                "isprobability": false,
                "generatemin": -1,
                "generatemax": -1,
                "isreplicated": false,
                "clonenr": 1,
                "isreplicatecandidate": false,
                "isoriginal": false,
                "children": [
                    {
                        "description": "mini_cadence",
                        "isreplacecandidate": true,
                        "isreplaced": false,
                        "value": -1,
                        "isprobability": false,
                        "generatemin": -1,
                        "generatemax": -1,
                        "isreplicated": false,
                        "clonenr": 1,
                        "isreplicatecandidate": false,
                        "isoriginal": false
                    }
                ]
            },
            {
                "description": "TONART_N",
                "isreplacecandidate": false,
                "isreplaced": false,
                "value": -1,
                "isprobability": false,
                "generatemin": 0,
                "generatemax": 4,
                "isreplicated": false,
                "clonenr": 1,
                "isreplicatecandidate": true,
                "isoriginal": false,
                "children": [
                    {
                        "description": "x",
                        "isreplacecandidate": false,
                        "isreplaced": false,
                        "value": -1,
                        "isprobability": false,
                        "generatemin": 1,
                        "generatemax": 1,
                        "isreplicated": false,
                        "clonenr": 1,
                        "isreplicatecandidate": true,
                        "isoriginal": false
                    },
                    {
                        "description": "TONART",
                        "isreplacecandidate": true,
                        "isreplaced": false,
                        "value": -1,
                        "isprobability": false,
                        "generatemin": -1,
                        "generatemax": -1,
                        "isreplicated": false,
                        "clonenr": 1,
                        "isreplicatecandidate": false,
                        "isoriginal": false
                    },
                    {
                        "description": "PV",
                        "isreplacecandidate": false,
                        "isreplaced": false,
                        "value": -1,
                        "isprobability": false,
                        "generatemin": -1,
                        "generatemax": -1,
                        "isreplicated": false,
                        "clonenr": 1,
                        "isreplicatecandidate": false,
                        "isoriginal": false
                    },
                    {
                        "description": "x",
                        "isreplacecandidate": false,
                        "isreplaced": false,
                        "value": -1,
                        "isprobability": false,
                        "generatemin": 1,
                        "generatemax": 1,
                        "isreplicated": false,
                        "clonenr": 1,
                        "isreplicatecandidate": true,
                        "isoriginal": false
                    },
                    {
                        "description": "mini_cadence",
                        "isreplacecandidate": true,
                        "isreplaced": false,
                        "value": -1,
                        "isprobability": false,
                        "generatemin": -1,
                        "generatemax": -1,
                        "isreplicated": false,
                        "clonenr": 1,
                        "isreplicatecandidate": false,
                        "isoriginal": false
                    },
                    {
                        "description": "x",
                        "isreplacecandidate": false,
                        "isreplaced": false,
                        "value": -1,
                        "isprobability": false,
                        "generatemin": 1,
                        "generatemax": 1,
                        "isreplicated": false,
                        "clonenr": 1,
                        "isreplicatecandidate": true,
                        "isoriginal": false
                    }
                ]
            },
            {
                "description": "TONART_A",
                "isreplacecandidate": false,
                "isreplaced": false,
                "value": -1,
                "isprobability": false,
                "generatemin": -1,
                "generatemax": -1,
                "isreplicated": false,
                "clonenr": 1,
                "isreplicatecandidate": false,
                "isoriginal": false,
                "children": [
                    {
                        "description": "x",
                        "isreplacecandidate": false,
                        "isreplaced": false,
                        "value": -1,
                        "isprobability": false,
                        "generatemin": 1,
                        "generatemax": 1,
                        "isreplicated": false,
                        "clonenr": 1,
                        "isreplicatecandidate": true,
                        "isoriginal": false
                    },
                    {
                        "description": "PV",
                        "isreplacecandidate": false,
                        "isreplaced": false,
                        "value": -1,
                        "isprobability": false,
                        "generatemin": -1,
                        "generatemax": -1,
                        "isreplicated": false,
                        "clonenr": 1,
                        "isreplicatecandidate": false,
                        "isoriginal": false
                    },
                    {
                        "description": "x",
                        "isreplacecandidate": false,
                        "isreplaced": false,
                        "value": -1,
                        "isprobability": false,
                        "generatemin": 1,
                        "generatemax": 1,
                        "isreplicated": false,
                        "clonenr": 1,
                        "isreplicatecandidate": true,
                        "isoriginal": false
                    },
                    {
                        "description": "mini_cadence",
                        "isreplacecandidate": true,
                        "isreplaced": false,
                        "value": -1,
                        "isprobability": false,
                        "generatemin": -1,
                        "generatemax": -1,
                        "isreplicated": false,
                        "clonenr": 1,
                        "isreplicatecandidate": false,
                        "isoriginal": false
                    },
                    {
                        "description": "x",
                        "isreplacecandidate": false,
                        "isreplaced": false,
                        "value": -1,
                        "isprobability": false,
                        "generatemin": 1,
                        "generatemax": 1,
                        "isreplicated": false,
                        "clonenr": 1,
                        "isreplicatecandidate": true,
                        "isoriginal": false
                    },
                    {
                        "description": "mini_cadence",
                        "isreplacecandidate": true,
                        "isreplaced": false,
                        "value": -1,
                        "isprobability": false,
                        "generatemin": -1,
                        "generatemax": -1,
                        "isreplicated": false,
                        "clonenr": 1,
                        "isreplicatecandidate": false,
                        "isoriginal": false
                    }
                ]
            },
            {
                "description": "TONART_X",
                "isreplacecandidate": false,
                "isreplaced": false,
                "value": -1,
                "isprobability": false,
                "generatemin": -1,
                "generatemax": -1,
                "isreplicated": false,
                "clonenr": 1,
                "isreplicatecandidate": false,
                "isoriginal": false
            }
        ]
    },
    {
        "description": "song",
        "isreplacecandidate": false,
        "isreplaced": false,
        "value": -1,
        "isprobability": false,
        "generatemin": -1,
        "generatemax": -1,
        "isreplicated": false,
        "clonenr": 1,
        "isreplicatecandidate": false,
        "isoriginal": true,
        "children": [
            {
                "description": "META",
                "isreplacecandidate": false,
                "isreplaced": false,
                "value": -1,
                "isprobability": false,
                "generatemin": -1,
                "generatemax": -1,
                "isreplicated": false,
                "clonenr": 1,
                "isreplicatecandidate": false,
                "isoriginal": false,
                "children": [
                    {
                        "description": "TONART_A",
                        "isreplacecandidate": false,
                        "isreplaced": false,
                        "value": -1,
                        "isprobability": false,
                        "generatemin": -1,
                        "generatemax": -1,
                        "isreplicated": false,
                        "clonenr": 1,
                        "isreplicatecandidate": false,
                        "isoriginal": false,
                        "children": [
                            {
                                "description": "TONART",
                                "isreplacecandidate": true,
                                "isreplaced": false,
                                "value": -1,
                                "isprobability": false,
                                "generatemin": -1,
                                "generatemax": -1,
                                "isreplicated": false,
                                "clonenr": 1,
                                "isreplicatecandidate": false,
                                "isoriginal": false
                            }
                        ]
                    }
                ]
            },
            {
                "description": "START_S",
                "isreplacecandidate": false,
                "isreplaced": false,
                "value": -1,
                "isprobability": false,
                "generatemin": -1,
                "generatemax": -1,
                "isreplicated": false,
                "clonenr": 1,
                "isreplicatecandidate": false,
                "isoriginal": false
            },
            {
                "description": "PREDOM",
                "isreplacecandidate": false,
                "isreplaced": false,
                "value": -1,
                "isprobability": false,
                "generatemin": -1,
                "generatemax": -1,
                "isreplicated": false,
                "clonenr": 1,
                "isreplicatecandidate": false,
                "isoriginal": false
            },
            {
                "description": "SECTION",
                "isreplacecandidate": true,
                "isreplaced": false,
                "value": -1,
                "isprobability": false,
                "generatemin": -1,
                "generatemax": -1,
                "isreplicated": false,
                "clonenr": 1,
                "isreplicatecandidate": false,
                "isoriginal": false
            },
            {
                "description": "CONN",
                "isreplacecandidate": false,
                "isreplaced": false,
                "value": -1,
                "isprobability": false,
                "generatemin": -1,
                "generatemax": -1,
                "isreplicated": false,
                "clonenr": 1,
                "isreplicatecandidate": false,
                "isoriginal": false
            },
            {
                "description": "CAD",
                "isreplacecandidate": false,
                "isreplaced": false,
                "value": -1,
                "isprobability": false,
                "generatemin": -1,
                "generatemax": -1,
                "isreplicated": false,
                "clonenr": 1,
                "isreplicatecandidate": false,
                "isoriginal": false
            },
            {
                "description": "END_S",
                "isreplacecandidate": false,
                "isreplaced": false,
                "value": -1,
                "isprobability": false,
                "generatemin": -1,
                "generatemax": -1,
                "isreplicated": false,
                "clonenr": 1,
                "isreplicatecandidate": false,
                "isoriginal": false
            }
        ]
    }
]